<?xml version="1.0" encoding="UTF-8"?>
<?xml-stylesheet href="/xml/XSLT/operations-cars.xsl" type="text/xsl"?>
<!DOCTYPE operations-config SYSTEM "/xml/DTD/operations-cars.dtd">
<operations-config>
  <!--Written by JMRI version 4.26+R381c8dfc32 on Fri Mar 31 11:03:32 PDT 2023-->
  <roads>
    <road name="ACL" />
    <road name="AT&amp;SF" />
    <road name="B" />
    <road name="B&amp;A" />
    <road name="B&amp;O" />
    <road name="BX" />
    <road name="CNJ" />
    <road name="CS" />
    <road name="DL&amp;W" />
    <road name="EEI" />
    <road name="ER" />
    <road name="ESHP" />
    <road name="ESS" />
    <road name="ET" />
    <road name="FGEX" />
    <road name="GB" />
    <road name="HT" />
    <road name="LV" />
    <road name="M&amp;P" />
    <road name="MWK" />
    <road name="NYC" />
    <road name="NYNH&amp;H" />
    <road name="P&amp;R" />
    <road name="PC" />
    <road name="PFEX" />
    <road name="PGCC" />
    <road name="PL" />
    <road name="PRR" />
    <road name="PRRMW" />
    <road name="PRRMoW" />
    <road name="SFRD" />
    <road name="SP" />
    <road name="TCX" />
    <road name="TELX" />
    <road name="TM" />
    <road name="UTLX" />
    <road name="WCC" />
    <road name="WJ&amp;S" />
    <road name="XM" />
    <road name="XX" />
  </roads>
  <types>
    <type name="B" />
    <type name="B60" />
    <type name="BE" />
    <type name="BX" />
    <type name="Bd" />
    <type name="Bdr" />
    <type name="Bn" />
    <type name="CA" />
    <type name="FM" />
    <type name="GB" />
    <type name="HK" />
    <type name="HT" />
    <type name="MA" />
    <type name="MWK" />
    <type name="NE" />
    <type name="NM" />
    <type name="Ok" />
    <type name="P54" />
    <type name="P70" />
    <type name="PB" />
    <type name="PC" />
    <type name="PS" />
    <type name="Pk" />
    <type name="RB" />
    <type name="RS" />
    <type name="TM" />
    <type name="XM" />
    <type name="XX" />
  </types>
  <colors>
    <color name="Black" />
    <color name="Blue" />
    <color name="Brown" />
    <color name="Gray" />
    <color name="Green" />
    <color name="Orange" />
    <color name="Purple" />
    <color name="Red" />
    <color name="Silver" />
    <color name="Tuscan" />
    <color name="White" />
    <color name="Yellow" />
  </colors>
  <lengths>
    <length value="32" />
    <length value="34" />
    <length value="36" />
    <length value="38" />
    <length value="40" />
    <length value="42" />
    <length value="44" />
    <length value="50" />
    <length value="51" />
    <length value="52" />
    <length value="54" />
    <length value="60" />
    <length value="70" />
  </lengths>
  <owners>
    <owner name="" />
  </owners>
  <loads>
    <defaults empty="E" load="L" />
    <load type="NE">
      <carLoad name="Empty" loadType="empty" />
      <carLoad name="Load" loadType="load" />
    </load>
    <load type="XX">
      <carLoad name="Empty" loadType="empty" />
      <carLoad name="Load" loadType="load" />
      <carLoad name="express" loadType="load" />
    </load>
    <load type="Bdr">
      <carLoad name="Empty" loadType="empty" />
      <carLoad name="Load" loadType="load" />
    </load>
    <load type="Bn">
      <carLoad name="Empty" loadType="empty" />
      <carLoad name="Load" loadType="load" />
      <carLoad name="express" loadType="load" />
    </load>
    <load type="RS">
      <carLoad name="Empty" loadType="empty" />
      <carLoad name="Load" loadType="load" />
      <carLoad name="iced" loadType="load" />
      <carLoad name="produce" loadType="load" />
    </load>
    <load type="P54">
      <carLoad name="Empty" loadType="empty" />
      <carLoad name="Load" loadType="load" />
    </load>
    <load type="FM">
      <carLoad name="Empty" loadType="empty" />
      <carLoad name="Load" loadType="load" />
      <carLoad name="Tarp" loadType="load" />
      <carLoad name="Tarp3" loadType="load" />
      <carLoad name="lumber stack" loadType="load" />
      <carLoad name="steel rods" loadType="load" />
    </load>
    <load type="XM">
      <carLoad name="Empty" loadType="empty" />
      <carLoad name="Load" loadType="load" />
      <carLoad name="goods" loadType="load" />
      <carLoad name="lcl" loadType="load" />
      <carLoad name="merchandise" loadType="load" />
      <carLoad name="steel products" loadType="load" />
    </load>
    <load type="Bd">
      <carLoad name="Empty" loadType="empty" />
      <carLoad name="Load" loadType="load" />
      <carLoad name="express" loadType="load" />
    </load>
    <load type="CA">
      <carLoad name="Empty" loadType="empty" />
      <carLoad name="Load" loadType="load" />
    </load>
    <load type="PS">
      <carLoad name="Empty" loadType="empty" />
      <carLoad name="Load" loadType="load" />
    </load>
    <load type="RB">
      <carLoad name="Empty" loadType="empty" />
      <carLoad name="Load" loadType="load" />
      <carLoad name="iced" loadType="load" />
      <carLoad name="produce" loadType="load" />
    </load>
    <load type="BX">
      <carLoad name="Empty" loadType="empty" />
      <carLoad name="Load" loadType="load" />
      <carLoad name="express" loadType="load" />
    </load>
    <load type="B">
      <carLoad name="Empty" loadType="empty" />
      <carLoad name="Load" loadType="load" />
    </load>
    <load type="Ok">
      <carLoad name="Empty" loadType="empty" />
      <carLoad name="Load" loadType="load" />
      <carLoad name="express" loadType="load" />
    </load>
    <load type="MWK">
      <carLoad name="Empty" loadType="empty" />
      <carLoad name="Load" loadType="load" />
    </load>
    <load type="HT">
      <carLoad name="Empty" loadType="empty" />
      <carLoad name="Load" loadType="load" />
    </load>
    <load type="GB">
      <carLoad name="Empty" loadType="empty" />
      <carLoad name="Load" loadType="load" />
      <carLoad name="Milled timber" loadType="load" />
      <carLoad name="Tarp" loadType="load" />
      <carLoad name="Tarp3" loadType="load" />
      <carLoad name="cinders" loadType="load" />
      <carLoad name="sand" loadType="load" />
      <carLoad name="steel rods" loadType="load" />
    </load>
    <load type="PC">
      <carLoad name="Empty" loadType="empty" />
      <carLoad name="Load" loadType="load" />
    </load>
    <load type="PB">
      <carLoad name="Empty" loadType="empty" />
      <carLoad name="Load" loadType="load" />
    </load>
    <load type="MA">
      <carLoad name="Empty" loadType="empty" />
      <carLoad name="Load" loadType="load" />
      <carLoad name="mail" loadType="load" />
    </load>
    <load type="B60">
      <carLoad name="Empty" loadType="empty" />
      <carLoad name="Load" loadType="load" />
      <carLoad name="express" loadType="load" />
    </load>
    <load type="HK">
      <carLoad name="Empty" loadType="empty" />
      <carLoad name="Load" loadType="load" />
      <carLoad name="coal2" loadType="load" />
    </load>
    <load type="NM">
      <carLoad name="Empty" loadType="empty" />
      <carLoad name="Load" loadType="load" />
    </load>
    <load type="Pk">
      <carLoad name="Empty" loadType="empty" />
      <carLoad name="Load" loadType="load" />
    </load>
    <load type="TM">
      <carLoad name="Empty" loadType="empty" />
      <carLoad name="Load" loadType="load" />
      <carLoad name="fuel" loadType="load" />
    </load>
    <load type="P70">
      <carLoad name="Empty" loadType="empty" />
      <carLoad name="Load" loadType="load" />
    </load>
    <load type="BE">
      <carLoad name="Empty" loadType="empty" />
      <carLoad name="Load" loadType="load" />
      <carLoad name="express" loadType="load" />
    </load>
  </loads>
  <newKernels>
    <kernel name="R1" />
    <kernel name="R2" />
    <kernel name="R3" />
    <kernel name="R4" />
    <kernel name="R5" />
    <kernel name="R6" />
    <kernel name="R7" />
  </newKernels>
  <options />
  <cars>
    <car id="ACL0360" roadName="ACL" roadNumber="0360" type="XM" length="40" color="Red" weight="2" weightTons="40" locationId="7" secLocationId="7s2" moves="0" date="" selected="false" load="E" />
    <car id="ACL0395" roadName="ACL" roadNumber="0395" type="GB" length="40" color="Red" weight="2" weightTons="40" locationId="11" secLocationId="11s1" moves="0" date="" selected="false" load="E" />
    <car id="ACL1418" roadName="ACL" roadNumber="1418" type="GB" length="40" color="Red" weight="2" weightTons="40" locationId="11" secLocationId="11s2" moves="0" date="" selected="false" load="E" />
    <car id="ACL2039" roadName="ACL" roadNumber="2039" type="XM" length="40" color="Red" weight="2" weightTons="40" locationId="5" secLocationId="5s2" moves="0" date="" selected="false" load="goods" />
    <car id="ACL3944" roadName="ACL" roadNumber="3944" type="XM" length="40" color="Red" weight="2" weightTons="40" locationId="11" secLocationId="11s4" moves="0" date="" selected="false" load="E" />
    <car id="ACL5093" roadName="ACL" roadNumber="5093" type="FM" length="40" color="Red" weight="2" weightTons="40" locationId="5" secLocationId="5s3" moves="0" date="" selected="false" load="Empty" />
    <car id="ACL6195" roadName="ACL" roadNumber="6195" type="GB" length="40" color="Red" weight="2" weightTons="40" locationId="7" secLocationId="7s2" moves="0" date="" selected="false" load="E" />
    <car id="ACL7510" roadName="ACL" roadNumber="7510" type="XM" length="40" color="Red" weight="2" weightTons="40" locationId="9" secLocationId="9s2" moves="0" date="" selected="false" load="E" />
    <car id="ACL7836" roadName="ACL" roadNumber="7836" type="GB" length="40" color="Red" weight="2" weightTons="40" locationId="2" secLocationId="2s1" moves="0" date="" selected="false" load="cinders" />
    <car id="ACL8139" roadName="ACL" roadNumber="8139" type="XM" length="40" color="Red" weight="2" weightTons="40" locationId="11" secLocationId="11s3" moves="0" date="" selected="false" load="E" />
    <car id="AT&amp;SF0204" roadName="AT&amp;SF" roadNumber="0204" type="GB" length="40" color="Red" weight="2" weightTons="40" locationId="11" secLocationId="11s4" moves="0" date="" selected="false" load="E" />
    <car id="AT&amp;SF8248" roadName="AT&amp;SF" roadNumber="8248" type="XM" length="40" color="Red" weight="2" weightTons="40" locationId="8" secLocationId="8s2" moves="0" date="" selected="false" load="E" />
    <car id="AT&amp;SF8501" roadName="AT&amp;SF" roadNumber="8501" type="XM" length="40" color="Red" weight="2" weightTons="40" locationId="3" secLocationId="3s2" moves="0" date="" selected="false" load="steel products" />
    <car id="AT&amp;SF9192" roadName="AT&amp;SF" roadNumber="9192" type="GB" length="40" color="Red" weight="2" weightTons="40" locationId="2" secLocationId="2s5" moves="0" date="" selected="false" load="Empty" />
    <car id="B&amp;A0591" roadName="B&amp;A" roadNumber="0591" type="XM" length="40" color="Red" weight="2" weightTons="40" locationId="11" secLocationId="11s2" moves="0" date="" selected="false" load="E" />
    <car id="B&amp;A1434" roadName="B&amp;A" roadNumber="1434" type="XM" length="40" color="Red" weight="2" weightTons="40" locationId="9" secLocationId="9s2" moves="0" date="" selected="false" load="E" />
    <car id="B&amp;A2122" roadName="B&amp;A" roadNumber="2122" type="XM" length="40" color="Red" weight="2" weightTons="40" locationId="7" secLocationId="7s2" moves="0" date="" selected="false" load="E" />
    <car id="B&amp;A2789" roadName="B&amp;A" roadNumber="2789" type="FM" length="40" color="Red" weight="2" weightTons="40" locationId="11" secLocationId="11s3" moves="0" date="" selected="false" load="E" />
    <car id="B&amp;A3657" roadName="B&amp;A" roadNumber="3657" type="GB" length="40" color="Red" weight="2" weightTons="40" locationId="2" secLocationId="2s3" moves="0" date="" selected="false" load="Empty" />
    <car id="B&amp;A4384" roadName="B&amp;A" roadNumber="4384" type="XM" length="40" color="Red" weight="2" weightTons="40" locationId="9" secLocationId="9s2" moves="0" date="" selected="false" load="E" />
    <car id="B&amp;A5360" roadName="B&amp;A" roadNumber="5360" type="FM" length="40" color="Red" weight="2" weightTons="40" locationId="2" secLocationId="2s5" moves="0" date="" selected="false" load="Empty" />
    <car id="B&amp;A5607" roadName="B&amp;A" roadNumber="5607" type="GB" length="40" color="Red" weight="2" weightTons="40" locationId="11" secLocationId="11s4" moves="0" date="" selected="false" load="E" />
    <car id="B&amp;A5690" roadName="B&amp;A" roadNumber="5690" type="XM" length="40" color="Red" weight="2" weightTons="40" locationId="11" secLocationId="11s2" moves="0" date="" selected="false" load="E" />
    <car id="B&amp;O0125" roadName="B&amp;O" roadNumber="0125" type="XM" length="40" color="Red" weight="2" weightTons="40" locationId="5" secLocationId="5s2" moves="0" date="" selected="false" load="goods" />
    <car id="B&amp;O0263" roadName="B&amp;O" roadNumber="0263" type="HK" length="40" color="Red" weight="2" weightTons="40" locationId="11" secLocationId="11s1" moves="0" date="" selected="false" load="E" />
    <car id="B&amp;O1107" roadName="B&amp;O" roadNumber="1107" type="HK" length="40" color="Red" weight="2" weightTons="40" locationId="11" secLocationId="11s3" moves="0" date="" selected="false" load="E" />
    <car id="B&amp;O1529" roadName="B&amp;O" roadNumber="1529" type="XM" length="40" color="Red" weight="2" weightTons="40" locationId="5" secLocationId="5s5" moves="0" date="" selected="false" load="goods" />
    <car id="B&amp;O1876" roadName="B&amp;O" roadNumber="1876" type="HK" length="40" color="Red" weight="2" weightTons="40" locationId="3" secLocationId="3s1" moves="0" date="" selected="false" load="Empty" />
    <car id="B&amp;O1911" roadName="B&amp;O" roadNumber="1911" type="XM" length="40" color="Red" weight="2" weightTons="40" locationId="8" secLocationId="8s2" moves="0" date="" selected="false" load="E" />
    <car id="B&amp;O3291" roadName="B&amp;O" roadNumber="3291" type="FM" length="40" color="Red" weight="2" weightTons="40" locationId="9" secLocationId="9s2" moves="0" date="" selected="false" load="E" />
    <car id="B&amp;O3502" roadName="B&amp;O" roadNumber="3502" type="HK" length="40" color="Red" weight="2" weightTons="40" locationId="11" secLocationId="11s4" moves="0" date="" selected="false" load="E" />
    <car id="B&amp;O3864" roadName="B&amp;O" roadNumber="3864" type="HK" length="40" color="Red" weight="2" weightTons="40" locationId="5" secLocationId="5s4" moves="0" date="" selected="false" load="Empty" />
    <car id="B&amp;O4021" roadName="B&amp;O" roadNumber="4021" type="XM" length="40" color="Red" weight="2" weightTons="40" locationId="7" secLocationId="7s2" moves="0" date="" selected="false" load="E" />
    <car id="B&amp;O4601" roadName="B&amp;O" roadNumber="4601" type="HK" length="40" color="Red" weight="2" weightTons="40" locationId="2" secLocationId="2s2" moves="0" date="" selected="false" load="Empty" />
    <car id="B&amp;O5413" roadName="B&amp;O" roadNumber="5413" type="XM" length="40" color="Red" weight="2" weightTons="40" locationId="5" secLocationId="5s2" moves="0" date="" selected="false" load="goods" />
    <car id="B&amp;O5501" roadName="B&amp;O" roadNumber="5501" type="HK" length="40" color="Red" weight="2" weightTons="40" locationId="11" secLocationId="11s3" moves="0" date="" selected="false" load="E" />
    <car id="B&amp;O5953" roadName="B&amp;O" roadNumber="5953" type="HK" length="40" color="Red" weight="2" weightTons="40" locationId="11" secLocationId="11s3" moves="0" date="" selected="false" load="E" />
    <car id="B&amp;O6073" roadName="B&amp;O" roadNumber="6073" type="HK" length="40" color="Red" weight="2" weightTons="40" locationId="4" secLocationId="4s1" moves="0" date="" selected="false" load="E" />
    <car id="B&amp;O6457" roadName="B&amp;O" roadNumber="6457" type="HK" length="40" color="Red" weight="2" weightTons="40" locationId="5" secLocationId="5s4" moves="0" date="" selected="false" load="Empty" />
    <car id="B&amp;O6978" roadName="B&amp;O" roadNumber="6978" type="HK" length="40" color="Red" weight="2" weightTons="40" locationId="8" secLocationId="8s2" moves="0" date="" selected="false" load="E" />
    <car id="B&amp;O7676" roadName="B&amp;O" roadNumber="7676" type="HK" length="40" color="Red" weight="2" weightTons="40" locationId="4" secLocationId="4s1" moves="0" date="" selected="false" load="E" />
    <car id="B&amp;O8552" roadName="B&amp;O" roadNumber="8552" type="HK" length="40" color="Red" weight="2" weightTons="40" locationId="11" secLocationId="11s1" moves="0" date="" selected="false" load="E" />
    <car id="B&amp;O8996" roadName="B&amp;O" roadNumber="8996" type="HK" length="40" color="Red" weight="2" weightTons="40" locationId="11" secLocationId="11s3" moves="0" date="" selected="false" load="E" />
    <car id="B&amp;O9336" roadName="B&amp;O" roadNumber="9336" type="HK" length="40" color="Red" weight="2" weightTons="40" locationId="8" secLocationId="8s2" moves="0" date="" selected="false" load="E" />
    <car id="CNJ2995" roadName="CNJ" roadNumber="2995" type="GB" length="40" color="Red" weight="2" weightTons="40" locationId="2" secLocationId="2s5" moves="0" date="" selected="false" load="Empty" />
    <car id="CNJ5227" roadName="CNJ" roadNumber="5227" type="XM" length="40" color="Red" weight="2" weightTons="40" locationId="11" secLocationId="11s4" moves="0" date="" selected="false" load="E" />
    <car id="CNJ9642" roadName="CNJ" roadNumber="9642" type="XM" length="40" color="Red" weight="2" weightTons="40" locationId="11" secLocationId="11s2" moves="0" date="" selected="false" load="E" />
    <car id="CS0073" roadName="CS" roadNumber="0073" type="XM" length="40" color="Red" weight="2" weightTons="40" locationId="8" secLocationId="8s2" moves="0" date="" selected="false" load="E" />
    <car id="CS1705" roadName="CS" roadNumber="1705" type="GB" length="40" color="Red" weight="2" weightTons="40" locationId="4" secLocationId="4s1" moves="0" date="" selected="false" load="E" />
    <car id="CS1725" roadName="CS" roadNumber="1725" type="XM" length="40" color="Red" weight="2" weightTons="40" locationId="11" secLocationId="11s4" moves="0" date="" selected="false" load="E" />
    <car id="CS3014" roadName="CS" roadNumber="3014" type="XM" length="40" color="Red" weight="2" weightTons="40" locationId="4" secLocationId="4s1" moves="0" date="" selected="false" load="E" />
    <car id="CS3576" roadName="CS" roadNumber="3576" type="XM" length="40" color="Red" weight="2" weightTons="40" locationId="11" secLocationId="11s5" moves="0" date="" selected="false" load="E" />
    <car id="CS5642" roadName="CS" roadNumber="5642" type="XM" length="40" color="Red" weight="2" weightTons="40" locationId="9" secLocationId="9s2" moves="0" date="" selected="false" load="E" />
    <car id="CS5888" roadName="CS" roadNumber="5888" type="GB" length="40" color="Red" weight="2" weightTons="40" locationId="7" secLocationId="7s2" moves="0" date="" selected="false" load="E" />
    <car id="CS5981" roadName="CS" roadNumber="5981" type="XM" length="40" color="Red" weight="2" weightTons="40" locationId="9" secLocationId="9s2" moves="0" date="" selected="false" load="E" />
    <car id="CS5997" roadName="CS" roadNumber="5997" type="GB" length="40" color="Red" weight="2" weightTons="40" locationId="2" secLocationId="2s5" moves="0" date="" selected="false" load="Empty" />
    <car id="CS6469" roadName="CS" roadNumber="6469" type="XM" length="40" color="Red" weight="2" weightTons="40" locationId="11" secLocationId="11s2" moves="0" date="" selected="false" load="E" />
    <car id="CS8963" roadName="CS" roadNumber="8963" type="XM" length="40" color="Red" weight="2" weightTons="40" locationId="9" secLocationId="9s2" moves="0" date="" selected="false" load="E" />
    <car id="CS9474" roadName="CS" roadNumber="9474" type="XM" length="40" color="Red" weight="2" weightTons="40" locationId="11" secLocationId="11s2" moves="0" date="" selected="false" load="E" />
    <car id="DL&amp;W0237" roadName="DL&amp;W" roadNumber="0237" type="XM" length="40" color="Red" weight="2" weightTons="40" locationId="9" secLocationId="9s2" moves="0" date="" selected="false" load="E" />
    <car id="DL&amp;W5996" roadName="DL&amp;W" roadNumber="5996" type="XM" length="40" color="Red" weight="2" weightTons="40" locationId="7" secLocationId="7s2" moves="0" date="" selected="false" load="E" />
    <car id="DL&amp;W6790" roadName="DL&amp;W" roadNumber="6790" type="XM" length="40" color="Red" weight="2" weightTons="40" locationId="9" secLocationId="9s2" moves="0" date="" selected="false" load="E" />
    <car id="DL&amp;W7085" roadName="DL&amp;W" roadNumber="7085" type="XM" length="40" color="Red" weight="2" weightTons="40" locationId="8" secLocationId="8s2" moves="0" date="" selected="false" load="E" />
    <car id="DL&amp;W7242" roadName="DL&amp;W" roadNumber="7242" type="XM" length="40" color="Red" weight="2" weightTons="40" locationId="11" secLocationId="11s2" moves="0" date="" selected="false" load="E" />
    <car id="DL&amp;W7977" roadName="DL&amp;W" roadNumber="7977" type="XM" length="40" color="Red" weight="2" weightTons="40" locationId="11" secLocationId="11s5" moves="0" date="" selected="false" load="E" />
    <car id="ER2343" roadName="ER" roadNumber="2343" type="XM" length="40" color="Red" weight="2" weightTons="40" locationId="5" secLocationId="5s6" moves="0" date="" selected="false" load="lcl" />
    <car id="ER2798" roadName="ER" roadNumber="2798" type="XM" length="40" color="Red" weight="2" weightTons="40" locationId="11" secLocationId="11s4" moves="0" date="" selected="false" load="E" />
    <car id="ER3741" roadName="ER" roadNumber="3741" type="XM" length="40" color="Red" weight="2" weightTons="40" locationId="11" secLocationId="11s2" moves="0" date="" selected="false" load="E" />
    <car id="ER5365" roadName="ER" roadNumber="5365" type="GB" length="40" color="Red" weight="2" weightTons="40" locationId="2" secLocationId="2s3" moves="0" date="" selected="false" load="Empty" />
    <car id="ER7426" roadName="ER" roadNumber="7426" type="FM" length="40" color="Red" weight="2" weightTons="40" locationId="11" secLocationId="11s3" moves="0" date="" selected="false" load="E" />
    <car id="ER7904" roadName="ER" roadNumber="7904" type="GB" length="40" color="Red" weight="2" weightTons="40" locationId="11" secLocationId="11s3" moves="0" date="" selected="false" load="E" />
    <car id="ER9009" roadName="ER" roadNumber="9009" type="XM" length="40" color="Red" weight="2" weightTons="40" locationId="9" secLocationId="9s2" moves="0" date="" selected="false" load="E" />
    <car id="FGEX0464" roadName="FGEX" roadNumber="0464" type="RS" length="40" color="Red" weight="2" weightTons="40" locationId="4" secLocationId="4s1" moves="0" date="" selected="false" kernel="R4" load="E" />
    <car id="FGEX0775" roadName="FGEX" roadNumber="0775" type="RB" length="40" color="Red" weight="2" weightTons="40" locationId="2" secLocationId="2s12" moves="0" date="" selected="false" kernel="R6" load="iced" />
    <car id="FGEX0857" roadName="FGEX" roadNumber="0857" type="RB" length="40" color="Red" weight="2" weightTons="40" locationId="12" secLocationId="12s3" moves="0" date="" selected="false" kernel="R7" leadKernel="true" load="E" />
    <car id="FGEX0914" roadName="FGEX" roadNumber="0914" type="RB" length="40" color="Red" weight="2" weightTons="40" locationId="4" secLocationId="4s1" moves="0" date="" selected="false" kernel="R4" leadKernel="true" load="E" />
    <car id="FGEX1013" roadName="FGEX" roadNumber="1013" type="RB" length="40" color="Red" weight="2" weightTons="40" locationId="12" secLocationId="12s3" moves="0" date="" selected="false" kernel="R3" load="E" />
    <car id="FGEX1072" roadName="FGEX" roadNumber="1072" type="RB" length="40" color="Red" weight="2" weightTons="40" locationId="12" secLocationId="12s3" moves="0" date="" selected="false" kernel="R7" load="E" />
    <car id="FGEX1417" roadName="FGEX" roadNumber="1417" type="RS" length="40" color="Red" weight="2" weightTons="40" locationId="12" secLocationId="12s3" moves="0" date="" selected="false" kernel="R1" load="E" />
    <car id="FGEX1530" roadName="FGEX" roadNumber="1530" type="RB" length="40" color="Red" weight="2" weightTons="40" locationId="12" secLocationId="12s3" moves="0" date="" selected="false" kernel="R1" load="E" />
    <car id="FGEX1605" roadName="FGEX" roadNumber="1605" type="RS" length="40" color="Red" weight="2" weightTons="40" locationId="12" secLocationId="12s3" moves="0" date="" selected="false" kernel="R7" load="E" />
    <car id="FGEX1736" roadName="FGEX" roadNumber="1736" type="RB" length="40" color="Red" weight="2" weightTons="40" locationId="6" secLocationId="6s3" moves="0" date="" selected="false" kernel="R5" load="produce" />
    <car id="FGEX1756" roadName="FGEX" roadNumber="1756" type="RS" length="40" color="Red" weight="2" weightTons="40" locationId="12" secLocationId="12s3" moves="0" date="" selected="false" kernel="R7" load="E" />
    <car id="FGEX1781" roadName="FGEX" roadNumber="1781" type="RS" length="40" color="Red" weight="2" weightTons="40" locationId="6" secLocationId="6s3" moves="0" date="" selected="false" kernel="R5" load="produce" />
    <car id="FGEX1782" roadName="FGEX" roadNumber="1782" type="RB" length="40" color="Red" weight="2" weightTons="40" locationId="12" secLocationId="12s3" moves="0" date="" selected="false" kernel="R1" leadKernel="true" load="E" />
    <car id="FGEX1802" roadName="FGEX" roadNumber="1802" type="RS" length="40" color="Red" weight="2" weightTons="40" locationId="12" secLocationId="12s3" moves="0" date="" selected="false" kernel="R7" load="E" />
    <car id="FGEX1842" roadName="FGEX" roadNumber="1842" type="RB" length="40" color="Red" weight="2" weightTons="40" locationId="6" secLocationId="6s3" moves="0" date="" selected="false" kernel="R5" load="produce" />
    <car id="FGEX2108" roadName="FGEX" roadNumber="2108" type="RB" length="40" color="Red" weight="2" weightTons="40" locationId="4" secLocationId="4s1" moves="0" date="" selected="false" kernel="R4" load="E" />
    <car id="FGEX2140" roadName="FGEX" roadNumber="2140" type="RS" length="40" color="Red" weight="2" weightTons="40" locationId="4" secLocationId="4s1" moves="0" date="" selected="false" kernel="R4" load="E" />
    <car id="FGEX2192" roadName="FGEX" roadNumber="2192" type="RS" length="40" color="Red" weight="2" weightTons="40" locationId="12" secLocationId="12s3" moves="0" date="" selected="false" kernel="R1" load="E" />
    <car id="FGEX2300" roadName="FGEX" roadNumber="2300" type="RS" length="40" color="Red" weight="2" weightTons="40" locationId="2" secLocationId="2s12" moves="0" date="" selected="false" kernel="R6" load="iced" />
    <car id="FGEX2420" roadName="FGEX" roadNumber="2420" type="RS" length="40" color="Red" weight="2" weightTons="40" locationId="2" secLocationId="2s12" moves="0" date="" selected="false" kernel="R6" load="iced" />
    <car id="FGEX2504" roadName="FGEX" roadNumber="2504" type="RB" length="40" color="Red" weight="2" weightTons="40" locationId="4" secLocationId="4s1" moves="0" date="" selected="false" kernel="R4" load="E" />
    <car id="FGEX2534" roadName="FGEX" roadNumber="2534" type="RB" length="40" color="Red" weight="2" weightTons="40" locationId="2" secLocationId="2s12" moves="0" date="" selected="false" kernel="R6" load="iced" />
    <car id="FGEX2719" roadName="FGEX" roadNumber="2719" type="RB" length="40" color="Red" weight="2" weightTons="40" locationId="12" secLocationId="12s3" moves="0" date="" selected="false" kernel="R1" load="E" />
    <car id="FGEX2746" roadName="FGEX" roadNumber="2746" type="RB" length="40" color="Red" weight="2" weightTons="40" locationId="2" secLocationId="2s12" moves="0" date="" selected="false" kernel="R6" load="iced" />
    <car id="FGEX2756" roadName="FGEX" roadNumber="2756" type="RS" length="40" color="Red" weight="2" weightTons="40" locationId="12" secLocationId="12s3" moves="0" date="" selected="false" kernel="R1" load="E" />
    <car id="FGEX2851" roadName="FGEX" roadNumber="2851" type="RB" length="40" color="Red" weight="2" weightTons="40" locationId="2" secLocationId="2s12" moves="0" date="" selected="false" kernel="R6" load="iced" />
    <car id="FGEX3069" roadName="FGEX" roadNumber="3069" type="RS" length="40" color="Red" weight="2" weightTons="40" locationId="12" secLocationId="12s3" moves="0" date="" selected="false" kernel="R3" load="E" />
    <car id="FGEX3237" roadName="FGEX" roadNumber="3237" type="RB" length="40" color="Red" weight="2" weightTons="40" locationId="12" secLocationId="12s3" moves="0" date="" selected="false" kernel="R7" load="E" />
    <car id="FGEX3250" roadName="FGEX" roadNumber="3250" type="RS" length="40" color="Red" weight="2" weightTons="40" locationId="4" secLocationId="4s1" moves="0" date="" selected="false" kernel="R4" load="E" />
    <car id="FGEX3251" roadName="FGEX" roadNumber="3251" type="RB" length="40" color="Red" weight="2" weightTons="40" locationId="2" secLocationId="2s12" moves="0" date="" selected="false" kernel="R6" load="iced" />
    <car id="FGEX3887" roadName="FGEX" roadNumber="3887" type="RB" length="40" color="Red" weight="2" weightTons="40" locationId="6" secLocationId="6s3" moves="0" date="" selected="false" kernel="R5" load="produce" />
    <car id="FGEX3994" roadName="FGEX" roadNumber="3994" type="RB" length="40" color="Red" weight="2" weightTons="40" locationId="12" secLocationId="12s3" moves="0" date="" selected="false" kernel="R7" load="E" />
    <car id="FGEX4338" roadName="FGEX" roadNumber="4338" type="RS" length="40" color="Red" weight="2" weightTons="40" locationId="6" secLocationId="6s3" moves="0" date="" selected="false" kernel="R5" load="produce" />
    <car id="FGEX4406" roadName="FGEX" roadNumber="4406" type="RS" length="40" color="Red" weight="2" weightTons="40" locationId="6" secLocationId="6s3" moves="0" date="" selected="false" kernel="R5" load="produce" />
    <car id="FGEX4409" roadName="FGEX" roadNumber="4409" type="RB" length="40" color="Red" weight="2" weightTons="40" locationId="12" secLocationId="12s3" moves="0" date="" selected="false" kernel="R7" load="E" />
    <car id="FGEX4540" roadName="FGEX" roadNumber="4540" type="RS" length="40" color="Red" weight="2" weightTons="40" locationId="12" secLocationId="12s3" moves="0" date="" selected="false" kernel="R1" load="E" />
    <car id="FGEX4555" roadName="FGEX" roadNumber="4555" type="RB" length="40" color="Red" weight="2" weightTons="40" locationId="12" secLocationId="12s3" moves="0" date="" selected="false" kernel="R1" load="E" />
    <car id="FGEX4699" roadName="FGEX" roadNumber="4699" type="RB" length="40" color="Red" weight="2" weightTons="40" locationId="12" secLocationId="12s3" moves="0" date="" selected="false" kernel="R7" load="E" />
    <car id="FGEX4774" roadName="FGEX" roadNumber="4774" type="RB" length="40" color="Red" weight="2" weightTons="40" locationId="12" secLocationId="12s3" moves="0" date="" selected="false" kernel="R3" load="E" />
    <car id="FGEX4784" roadName="FGEX" roadNumber="4784" type="RS" length="40" color="Red" weight="2" weightTons="40" locationId="4" secLocationId="4s1" moves="0" date="" selected="false" kernel="R4" load="E" />
    <car id="FGEX5306" roadName="FGEX" roadNumber="5306" type="RB" length="40" color="Red" weight="2" weightTons="40" locationId="6" secLocationId="6s3" moves="0" date="" selected="false" kernel="R5" load="produce" />
    <car id="FGEX5733" roadName="FGEX" roadNumber="5733" type="RB" length="40" color="Red" weight="2" weightTons="40" locationId="6" secLocationId="6s3" moves="0" date="" selected="false" kernel="R5" load="produce" />
    <car id="FGEX5863" roadName="FGEX" roadNumber="5863" type="RB" length="40" color="Red" weight="2" weightTons="40" locationId="12" secLocationId="12s3" moves="0" date="" selected="false" kernel="R1" load="E" />
    <car id="FGEX6112" roadName="FGEX" roadNumber="6112" type="RS" length="40" color="Red" weight="2" weightTons="40" locationId="4" secLocationId="4s1" moves="0" date="" selected="false" kernel="R4" load="E" />
    <car id="FGEX6135" roadName="FGEX" roadNumber="6135" type="RB" length="40" color="Red" weight="2" weightTons="40" locationId="2" secLocationId="2s12" moves="0" date="" selected="false" kernel="R6" load="iced" />
    <car id="FGEX6176" roadName="FGEX" roadNumber="6176" type="RB" length="40" color="Red" weight="2" weightTons="40" locationId="12" secLocationId="12s3" moves="0" date="" selected="false" kernel="R7" load="E" />
    <car id="FGEX6304" roadName="FGEX" roadNumber="6304" type="RB" length="40" color="Red" weight="2" weightTons="40" locationId="12" secLocationId="12s3" moves="0" date="" selected="false" kernel="R3" leadKernel="true" load="E" />
    <car id="FGEX6509" roadName="FGEX" roadNumber="6509" type="RB" length="40" color="Red" weight="2" weightTons="40" locationId="12" secLocationId="12s3" moves="0" date="" selected="false" kernel="R1" load="E" />
    <car id="FGEX6554" roadName="FGEX" roadNumber="6554" type="RB" length="40" color="Red" weight="2" weightTons="40" locationId="6" secLocationId="6s3" moves="0" date="" selected="false" kernel="R5" load="produce" />
    <car id="FGEX6661" roadName="FGEX" roadNumber="6661" type="RS" length="40" color="Red" weight="2" weightTons="40" locationId="12" secLocationId="12s3" moves="0" date="" selected="false" kernel="R3" load="E" />
    <car id="FGEX6669" roadName="FGEX" roadNumber="6669" type="RB" length="40" color="Red" weight="2" weightTons="40" locationId="4" secLocationId="4s1" moves="0" date="" selected="false" kernel="R4" load="E" />
    <car id="FGEX6983" roadName="FGEX" roadNumber="6983" type="RB" length="40" color="Red" weight="2" weightTons="40" locationId="4" secLocationId="4s1" moves="0" date="" selected="false" kernel="R4" load="E" />
    <car id="FGEX6993" roadName="FGEX" roadNumber="6993" type="RB" length="40" color="Red" weight="2" weightTons="40" locationId="6" secLocationId="6s3" moves="0" date="" selected="false" kernel="R5" leadKernel="true" load="produce" />
    <car id="FGEX7063" roadName="FGEX" roadNumber="7063" type="RS" length="40" color="Red" weight="2" weightTons="40" locationId="12" secLocationId="12s3" moves="0" date="" selected="false" kernel="R7" load="E" />
    <car id="FGEX7095" roadName="FGEX" roadNumber="7095" type="RB" length="40" color="Red" weight="2" weightTons="40" locationId="12" secLocationId="12s3" moves="0" date="" selected="false" kernel="R3" load="E" />
    <car id="FGEX7290" roadName="FGEX" roadNumber="7290" type="RB" length="40" color="Red" weight="2" weightTons="40" locationId="12" secLocationId="12s3" moves="0" date="" selected="false" kernel="R1" load="E" />
    <car id="FGEX7388" roadName="FGEX" roadNumber="7388" type="RS" length="40" color="Red" weight="2" weightTons="40" locationId="12" secLocationId="12s3" moves="0" date="" selected="false" kernel="R3" load="E" />
    <car id="FGEX7611" roadName="FGEX" roadNumber="7611" type="RB" length="40" color="Red" weight="2" weightTons="40" locationId="12" secLocationId="12s3" moves="0" date="" selected="false" kernel="R1" load="E" />
    <car id="FGEX7646" roadName="FGEX" roadNumber="7646" type="RB" length="40" color="Red" weight="2" weightTons="40" locationId="12" secLocationId="12s3" moves="0" date="" selected="false" kernel="R3" load="E" />
    <car id="FGEX7836" roadName="FGEX" roadNumber="7836" type="RB" length="40" color="Red" weight="2" weightTons="40" locationId="4" secLocationId="4s1" moves="0" date="" selected="false" kernel="R4" load="E" />
    <car id="FGEX7896" roadName="FGEX" roadNumber="7896" type="RB" length="40" color="Red" weight="2" weightTons="40" locationId="12" secLocationId="12s3" moves="0" date="" selected="false" kernel="R3" load="E" />
    <car id="FGEX7991" roadName="FGEX" roadNumber="7991" type="RS" length="40" color="Red" weight="2" weightTons="40" locationId="12" secLocationId="12s3" moves="0" date="" selected="false" kernel="R3" load="E" />
    <car id="FGEX8220" roadName="FGEX" roadNumber="8220" type="RS" length="40" color="Red" weight="2" weightTons="40" locationId="12" secLocationId="12s3" moves="0" date="" selected="false" kernel="R3" load="E" />
    <car id="FGEX8387" roadName="FGEX" roadNumber="8387" type="RS" length="40" color="Red" weight="2" weightTons="40" locationId="2" secLocationId="2s12" moves="0" date="" selected="false" kernel="R6" load="iced" />
    <car id="FGEX8617" roadName="FGEX" roadNumber="8617" type="RS" length="40" color="Red" weight="2" weightTons="40" locationId="6" secLocationId="6s3" moves="0" date="" selected="false" kernel="R5" load="produce" />
    <car id="FGEX8881" roadName="FGEX" roadNumber="8881" type="RB" length="40" color="Red" weight="2" weightTons="40" locationId="6" secLocationId="6s3" moves="0" date="" selected="false" kernel="R5" load="produce" />
    <car id="FGEX8990" roadName="FGEX" roadNumber="8990" type="RS" length="40" color="Red" weight="2" weightTons="40" locationId="12" secLocationId="12s3" moves="0" date="" selected="false" kernel="R7" load="E" />
    <car id="FGEX9054" roadName="FGEX" roadNumber="9054" type="RB" length="40" color="Red" weight="2" weightTons="40" locationId="4" secLocationId="4s1" moves="0" date="" selected="false" kernel="R4" load="E" />
    <car id="FGEX9060" roadName="FGEX" roadNumber="9060" type="RS" length="40" color="Red" weight="2" weightTons="40" locationId="2" secLocationId="2s12" moves="0" date="" selected="false" kernel="R6" load="iced" />
    <car id="FGEX9138" roadName="FGEX" roadNumber="9138" type="RB" length="40" color="Red" weight="2" weightTons="40" locationId="2" secLocationId="2s12" moves="0" date="" selected="false" kernel="R6" load="iced" />
    <car id="FGEX9586" roadName="FGEX" roadNumber="9586" type="RB" length="40" color="Red" weight="2" weightTons="40" locationId="2" secLocationId="2s12" moves="0" date="" selected="false" kernel="R6" leadKernel="true" load="iced" />
    <car id="FGEX9672" roadName="FGEX" roadNumber="9672" type="RB" length="40" color="Red" weight="2" weightTons="40" locationId="12" secLocationId="12s3" moves="0" date="" selected="false" kernel="R3" load="E" />
    <car id="LV7577" roadName="LV" roadNumber="7577" type="XM" length="40" color="Red" weight="2" weightTons="40" locationId="2" secLocationId="2s5" moves="0" date="" selected="false" load="goods" />
    <car id="M&amp;P1712" roadName="M&amp;P" roadNumber="1712" type="XM" length="40" color="Red" weight="2" weightTons="40" locationId="11" secLocationId="11s3" moves="0" date="" selected="false" load="E" />
    <car id="M&amp;P2664" roadName="M&amp;P" roadNumber="2664" type="XM" length="40" color="Red" weight="2" weightTons="40" locationId="11" secLocationId="11s4" moves="0" date="" selected="false" load="E" />
    <car id="M&amp;P3300" roadName="M&amp;P" roadNumber="3300" type="GB" length="40" color="Red" weight="2" weightTons="40" locationId="11" secLocationId="11s3" moves="0" date="" selected="false" load="E" />
    <car id="M&amp;P5577" roadName="M&amp;P" roadNumber="5577" type="XM" length="40" color="Red" weight="2" weightTons="40" locationId="11" secLocationId="11s3" moves="0" date="" selected="false" load="E" />
    <car id="M&amp;P6045" roadName="M&amp;P" roadNumber="6045" type="FM" length="40" color="Red" weight="2" weightTons="40" locationId="11" secLocationId="11s1" moves="0" date="" selected="false" load="E" />
    <car id="M&amp;P6808" roadName="M&amp;P" roadNumber="6808" type="XM" length="40" color="Red" weight="2" weightTons="40" locationId="11" secLocationId="11s4" moves="0" date="" selected="false" load="E" />
    <car id="M&amp;P8641" roadName="M&amp;P" roadNumber="8641" type="XM" length="40" color="Red" weight="2" weightTons="40" locationId="1" secLocationId="1s1" moves="0" date="" selected="false" load="E" />
    <car id="NYC0574" roadName="NYC" roadNumber="0574" type="GB" length="40" color="Red" weight="2" weightTons="40" locationId="11" secLocationId="11s2" moves="0" date="" selected="false" load="E" />
    <car id="NYC3866" roadName="NYC" roadNumber="3866" type="XM" length="40" color="Red" weight="2" weightTons="40" locationId="11" secLocationId="11s3" moves="0" date="" selected="false" load="E" />
    <car id="NYC4619" roadName="NYC" roadNumber="4619" type="XM" length="40" color="Red" weight="2" weightTons="40" locationId="4" secLocationId="4s1" moves="0" date="" selected="false" load="E" />
    <car id="NYC6203" roadName="NYC" roadNumber="6203" type="XM" length="40" color="Red" weight="2" weightTons="40" locationId="6" secLocationId="6s2" moves="0" date="" selected="false" load="lcl" />
    <car id="NYC7571" roadName="NYC" roadNumber="7571" type="GB" length="40" color="Red" weight="2" weightTons="40" locationId="7" secLocationId="7s2" moves="0" date="" selected="false" load="E" />
    <car id="NYC7835" roadName="NYC" roadNumber="7835" type="FM" length="40" color="Red" weight="2" weightTons="40" locationId="9" secLocationId="9s2" moves="0" date="" selected="false" load="E" />
    <car id="NYC9231" roadName="NYC" roadNumber="9231" type="XM" length="40" color="Red" weight="2" weightTons="40" locationId="11" secLocationId="11s2" moves="0" date="" selected="false" load="E" />
    <car id="NYNH&amp;H0256" roadName="NYNH&amp;H" roadNumber="0256" type="XM" length="40" color="Red" weight="2" weightTons="40" locationId="8" secLocationId="8s2" moves="0" date="" selected="false" load="E" />
    <car id="NYNH&amp;H0323" roadName="NYNH&amp;H" roadNumber="0323" type="XM" length="40" color="Red" weight="2" weightTons="40" locationId="9" secLocationId="9s2" moves="0" date="" selected="false" load="E" />
    <car id="NYNH&amp;H0540" roadName="NYNH&amp;H" roadNumber="0540" type="XM" length="40" color="Red" weight="2" weightTons="40" locationId="11" secLocationId="11s5" moves="0" date="" selected="false" load="E" />
    <car id="NYNH&amp;H3285" roadName="NYNH&amp;H" roadNumber="3285" type="GB" length="40" color="Red" weight="2" weightTons="40" locationId="9" secLocationId="9s2" moves="0" date="" selected="false" load="E" />
    <car id="NYNH&amp;H3502" roadName="NYNH&amp;H" roadNumber="3502" type="XM" length="40" color="Red" weight="2" weightTons="40" locationId="11" secLocationId="11s4" moves="0" date="" selected="false" load="E" />
    <car id="NYNH&amp;H4320" roadName="NYNH&amp;H" roadNumber="4320" type="GB" length="40" color="Red" weight="2" weightTons="40" locationId="3" secLocationId="3s2" moves="0" date="" selected="false" load="steel rods" />
    <car id="NYNH&amp;H4979" roadName="NYNH&amp;H" roadNumber="4979" type="XM" length="40" color="Red" weight="2" weightTons="40" locationId="2" secLocationId="2s5" moves="0" date="" selected="false" load="goods" />
    <car id="NYNH&amp;H8380" roadName="NYNH&amp;H" roadNumber="8380" type="GB" length="40" color="Red" weight="2" weightTons="40" locationId="11" secLocationId="11s1" moves="0" date="" selected="false" load="E" />
    <car id="NYNH&amp;H8947" roadName="NYNH&amp;H" roadNumber="8947" type="XM" length="40" color="Red" weight="2" weightTons="40" locationId="5" secLocationId="5s2" moves="0" date="" selected="false" load="goods" />
    <car id="P&amp;R1166" roadName="P&amp;R" roadNumber="1166" type="HK" length="40" color="Red" weight="2" weightTons="40" locationId="11" secLocationId="11s2" moves="0" date="" selected="false" load="E" />
    <car id="P&amp;R1315" roadName="P&amp;R" roadNumber="1315" type="XM" length="40" color="Red" weight="2" weightTons="40" locationId="2" secLocationId="2s8" moves="0" date="" selected="false" load="lcl" />
    <car id="P&amp;R2756" roadName="P&amp;R" roadNumber="2756" type="XM" length="40" color="Red" weight="2" weightTons="40" locationId="2" secLocationId="2s8" moves="0" date="" selected="false" load="lcl" />
    <car id="P&amp;R3532" roadName="P&amp;R" roadNumber="3532" type="GB" length="40" color="Red" weight="2" weightTons="40" locationId="8" secLocationId="8s2" moves="0" date="" selected="false" load="E" />
    <car id="P&amp;R5960" roadName="P&amp;R" roadNumber="5960" type="HK" length="40" color="Red" weight="2" weightTons="40" locationId="8" secLocationId="8s2" moves="0" date="" selected="false" load="E" />
    <car id="P&amp;R6575" roadName="P&amp;R" roadNumber="6575" type="HK" length="40" color="Red" weight="2" weightTons="40" locationId="8" secLocationId="8s2" moves="0" date="" selected="false" load="E" />
    <car id="P&amp;R7136" roadName="P&amp;R" roadNumber="7136" type="HK" length="40" color="Red" weight="2" weightTons="40" locationId="11" secLocationId="11s3" moves="0" date="" selected="false" load="E" />
    <car id="P&amp;R7172" roadName="P&amp;R" roadNumber="7172" type="XM" length="40" color="Red" weight="2" weightTons="40" locationId="11" secLocationId="11s5" moves="0" date="" selected="false" load="E" />
    <car id="P&amp;R7375" roadName="P&amp;R" roadNumber="7375" type="HK" length="40" color="Red" weight="2" weightTons="40" locationId="8" secLocationId="8s2" moves="0" date="" selected="false" load="E" />
    <car id="P&amp;R7622" roadName="P&amp;R" roadNumber="7622" type="XM" length="40" color="Red" weight="2" weightTons="40" locationId="8" secLocationId="8s2" moves="0" date="" selected="false" load="E" />
    <car id="P&amp;R8004" roadName="P&amp;R" roadNumber="8004" type="HK" length="40" color="Red" weight="2" weightTons="40" locationId="6" secLocationId="6s1" moves="0" date="" selected="false" load="Empty" />
    <car id="P&amp;R8518" roadName="P&amp;R" roadNumber="8518" type="XM" length="40" color="Red" weight="2" weightTons="40" locationId="11" secLocationId="11s4" moves="0" date="" selected="false" load="E" />
    <car id="P&amp;R9149" roadName="P&amp;R" roadNumber="9149" type="XM" length="40" color="Red" weight="2" weightTons="40" locationId="11" secLocationId="11s5" moves="0" date="" selected="false" load="E" />
    <car id="PGCC0575" roadName="PGCC" roadNumber="0575" type="HK" length="40" color="Red" weight="2" weightTons="40" locationId="11" secLocationId="11s3" moves="0" date="" selected="false" load="E" />
    <car id="PGCC1635" roadName="PGCC" roadNumber="1635" type="HK" length="40" color="Red" weight="2" weightTons="40" locationId="11" secLocationId="11s1" moves="0" date="" selected="false" load="E" />
    <car id="PGCC2474" roadName="PGCC" roadNumber="2474" type="HK" length="40" color="Red" weight="2" weightTons="40" locationId="5" secLocationId="5s4" moves="0" date="" selected="false" load="Empty" />
    <car id="PGCC3336" roadName="PGCC" roadNumber="3336" type="HK" length="40" color="Red" weight="2" weightTons="40" locationId="11" secLocationId="11s1" moves="0" date="" selected="false" load="E" />
    <car id="PGCC5648" roadName="PGCC" roadNumber="5648" type="HK" length="40" color="Red" weight="2" weightTons="40" locationId="11" secLocationId="11s1" moves="0" date="" selected="false" load="E" />
    <car id="PGCC7590" roadName="PGCC" roadNumber="7590" type="HK" length="40" color="Red" weight="2" weightTons="40" locationId="11" secLocationId="11s3" moves="0" date="" selected="false" load="E" />
    <car id="PGCC7891" roadName="PGCC" roadNumber="7891" type="HK" length="40" color="Red" weight="2" weightTons="40" locationId="5" secLocationId="5s4" moves="0" date="" selected="false" load="Empty" />
    <car id="PGCC9109" roadName="PGCC" roadNumber="9109" type="HK" length="40" color="Red" weight="2" weightTons="40" locationId="8" secLocationId="8s2" moves="0" date="" selected="false" load="E" />
    <car id="PL0919" roadName="PL" roadNumber="0919" type="GB" length="40" color="Red" weight="2" weightTons="40" locationId="11" secLocationId="11s2" moves="0" date="" selected="false" load="E" />
    <car id="PL2120" roadName="PL" roadNumber="2120" type="GB" length="40" color="Red" weight="2" weightTons="40" locationId="11" secLocationId="11s3" moves="0" date="" selected="false" load="E" />
    <car id="PL2128" roadName="PL" roadNumber="2128" type="FM" length="40" color="Red" weight="2" weightTons="40" locationId="11" secLocationId="11s1" moves="0" date="" selected="false" load="E" />
    <car id="PL2963" roadName="PL" roadNumber="2963" type="XM" length="40" color="Red" weight="2" weightTons="40" locationId="11" secLocationId="11s1" moves="0" date="" selected="false" load="E" />
    <car id="PL3670" roadName="PL" roadNumber="3670" type="GB" length="40" color="Red" weight="2" weightTons="40" locationId="3" secLocationId="3s2" moves="0" date="" selected="false" load="steel rods" />
    <car id="PL4071" roadName="PL" roadNumber="4071" type="FM" length="40" color="Red" weight="2" weightTons="40" locationId="9" secLocationId="9s2" moves="0" date="" selected="false" load="E" />
    <car id="PL5550" roadName="PL" roadNumber="5550" type="GB" length="40" color="Red" weight="2" weightTons="40" locationId="9" secLocationId="9s2" moves="0" date="" selected="false" load="E" />
    <car id="PL5884" roadName="PL" roadNumber="5884" type="XM" length="40" color="Red" weight="2" weightTons="40" locationId="2" secLocationId="2s8" moves="0" date="" selected="false" load="lcl" />
    <car id="PL6912" roadName="PL" roadNumber="6912" type="GB" length="40" color="Red" weight="2" weightTons="40" locationId="9" secLocationId="9s2" moves="0" date="" selected="false" load="E" />
    <car id="PL7266" roadName="PL" roadNumber="7266" type="XM" length="40" color="Red" weight="2" weightTons="40" locationId="7" secLocationId="7s2" moves="0" date="" selected="false" load="E" />
    <car id="PL8533" roadName="PL" roadNumber="8533" type="XM" length="40" color="Red" weight="2" weightTons="40" locationId="8" secLocationId="8s2" moves="0" date="" selected="false" load="E" />
    <car id="PRR0107" roadName="PRR" roadNumber="0107" type="Bd" length="40" color="Red" weight="2" weightTons="36" locationId="2" secLocationId="2s8" moves="0" date="" selected="false" passenger="true" load="express" />
    <car id="PRR0286" roadName="PRR" roadNumber="0286" type="P70" length="40" color="Red" weight="2" weightTons="40" locationId="8" secLocationId="8s3" moves="0" date="" selected="false" load="E" />
    <car id="PRR0364" roadName="PRR" roadNumber="0364" type="P70" length="40" color="Red" weight="2" weightTons="40" locationId="8" secLocationId="8s3" moves="0" date="" selected="false" load="E" />
    <car id="PRR0420" roadName="PRR" roadNumber="0420" type="XM" length="40" color="Red" weight="2" weightTons="40" locationId="8" secLocationId="8s2" moves="0" date="" selected="false" load="E" />
    <car id="PRR0449" roadName="PRR" roadNumber="0449" type="B60" length="40" color="Red" weight="2" weightTons="36" locationId="9" secLocationId="9s4" moves="0" date="" selected="false" passenger="true" load="E" />
    <car id="PRR0460" roadName="PRR" roadNumber="0460" type="XX" length="40" color="Red" weight="2" weightTons="40" locationId="4" secLocationId="4s1" moves="0" date="" selected="false" load="E" />
    <car id="PRR0618" roadName="PRR" roadNumber="0618" type="XM" length="40" color="Red" weight="2" weightTons="40" locationId="11" secLocationId="11s4" moves="0" date="" selected="false" load="E" />
    <car id="PRR0672" roadName="PRR" roadNumber="0672" type="TM" length="40" color="Red" weight="2" weightTons="40" locationId="7" secLocationId="7s2" moves="0" date="" selected="false" load="E" />
    <car id="PRR0736" roadName="PRR" roadNumber="0736" type="Bn" length="40" color="Red" weight="2" weightTons="36" locationId="9" secLocationId="9s4" moves="0" date="" selected="false" passenger="true" load="E" />
    <car id="PRR0838" roadName="PRR" roadNumber="0838" type="P54" length="40" color="Red" weight="2" weightTons="40" locationId="10" secLocationId="10s9" moves="0" date="" selected="false" load="E" />
    <car id="PRR1035" roadName="PRR" roadNumber="1035" type="XM" length="40" color="Red" weight="2" weightTons="40" locationId="9" secLocationId="9s2" moves="0" date="" selected="false" load="E" />
    <car id="PRR119" roadName="PRR" roadNumber="119" type="NM" length="40" color="Red" weight="2" weightTons="36" locationId="10" secLocationId="10s8" moves="0" date="" selected="false" caboose="true" load="E" />
    <car id="PRR1215" roadName="PRR" roadNumber="1215" type="XM" length="40" color="Red" weight="2" weightTons="40" locationId="8" secLocationId="8s2" moves="0" date="" selected="false" load="E" />
    <car id="PRR1219" roadName="PRR" roadNumber="1219" type="GB" length="40" color="Red" weight="2" weightTons="40" locationId="9" secLocationId="9s2" moves="0" date="" selected="false" load="E" />
    <car id="PRR1237" roadName="PRR" roadNumber="1237" type="GB" length="40" color="Red" weight="2" weightTons="40" locationId="9" secLocationId="9s2" moves="0" date="" selected="false" load="E" />
    <car id="PRR1844" roadName="PRR" roadNumber="1844" type="B60" length="40" color="Red" weight="2" weightTons="36" locationId="9" secLocationId="9s4" moves="0" date="" selected="false" passenger="true" load="E" />
    <car id="PRR1896" roadName="PRR" roadNumber="1896" type="TM" length="40" color="Red" weight="2" weightTons="40" locationId="5" secLocationId="5s7" moves="0" date="" selected="false" load="Empty" />
    <car id="PRR1942" roadName="PRR" roadNumber="1942" type="HK" length="40" color="Red" weight="2" weightTons="40" locationId="8" secLocationId="8s2" moves="0" date="" selected="false" load="E" />
    <car id="PRR1959" roadName="PRR" roadNumber="1959" type="Bn" length="40" color="Red" weight="2" weightTons="36" locationId="8" secLocationId="8s3" moves="0" date="" selected="false" passenger="true" load="E" />
    <car id="PRR206" roadName="PRR" roadNumber="206" type="NM" length="40" color="Red" weight="2" weightTons="36" locationId="10" secLocationId="10s8" moves="0" date="" selected="false" caboose="true" load="E" />
    <car id="PRR2238" roadName="PRR" roadNumber="2238" type="FM" length="40" color="Red" weight="2" weightTons="40" locationId="7" secLocationId="7s2" moves="0" date="" selected="false" load="E" />
    <car id="PRR2256" roadName="PRR" roadNumber="2256" type="CA" length="40" color="Red" weight="2" weightTons="36" locationId="9" secLocationId="9s4" moves="0" date="" selected="false" passenger="true" load="E" />
    <car id="PRR230" roadName="PRR" roadNumber="230" type="NE" length="40" color="Red" weight="2" weightTons="36" locationId="10" secLocationId="10s8" moves="0" date="" selected="false" caboose="true" load="E" />
    <car id="PRR235" roadName="PRR" roadNumber="235" type="NM" length="40" color="Red" weight="2" weightTons="36" locationId="10" secLocationId="10s8" moves="0" date="" selected="false" caboose="true" load="E" />
    <car id="PRR2450" roadName="PRR" roadNumber="2450" type="XX" length="40" color="Red" weight="2" weightTons="40" locationId="9" secLocationId="9s4" moves="0" date="" selected="false" load="E" />
    <car id="PRR2476" roadName="PRR" roadNumber="2476" type="GB" length="40" color="Red" weight="2" weightTons="40" locationId="9" secLocationId="9s2" moves="0" date="" selected="false" load="E" />
    <car id="PRR2490" roadName="PRR" roadNumber="2490" type="Bn" length="40" color="Red" weight="2" weightTons="36" locationId="9" secLocationId="9s4" moves="0" date="" selected="false" passenger="true" load="E" />
    <car id="PRR2598" roadName="PRR" roadNumber="2598" type="XM" length="40" color="Red" weight="2" weightTons="40" locationId="11" secLocationId="11s2" moves="0" date="" selected="false" load="E" />
    <car id="PRR2643" roadName="PRR" roadNumber="2643" type="FM" length="40" color="Red" weight="2" weightTons="40" locationId="5" secLocationId="5s3" moves="0" date="" selected="false" load="Empty" />
    <car id="PRR2727" roadName="PRR" roadNumber="2727" type="B60" length="40" color="Red" weight="2" weightTons="36" locationId="9" secLocationId="9s4" moves="0" date="" selected="false" passenger="true" load="E" />
    <car id="PRR2886" roadName="PRR" roadNumber="2886" type="P54" length="40" color="Red" weight="2" weightTons="40" locationId="10" secLocationId="10s9" moves="0" date="" selected="false" load="E" />
    <car id="PRR308" roadName="PRR" roadNumber="308" type="NE" length="40" color="Red" weight="2" weightTons="36" locationId="10" secLocationId="10s8" moves="0" date="" selected="false" caboose="true" load="E" />
    <car id="PRR3181" roadName="PRR" roadNumber="3181" type="XX" length="40" color="Red" weight="2" weightTons="40" locationId="8" secLocationId="8s3" moves="0" date="" selected="false" load="E" />
    <car id="PRR3375" roadName="PRR" roadNumber="3375" type="TM" length="40" color="Red" weight="2" weightTons="40" locationId="8" secLocationId="8s2" moves="0" date="" selected="false" load="E" />
    <car id="PRR3620" roadName="PRR" roadNumber="3620" type="B60" length="40" color="Red" weight="2" weightTons="36" locationId="2" secLocationId="2s6" moves="0" date="" selected="false" passenger="true" load="express" />
    <car id="PRR3637" roadName="PRR" roadNumber="3637" type="XX" length="40" color="Red" weight="2" weightTons="40" locationId="4" secLocationId="4s1" moves="0" date="" selected="false" load="E" />
    <car id="PRR3657" roadName="PRR" roadNumber="3657" type="Bn" length="40" color="Red" weight="2" weightTons="36" locationId="2" secLocationId="2s6" moves="0" date="" selected="false" passenger="true" load="express" />
    <car id="PRR386" roadName="PRR" roadNumber="386" type="NE" length="40" color="Red" weight="2" weightTons="36" locationId="8" secLocationId="8s2" moves="0" date="" selected="false" caboose="true" load="E" />
    <car id="PRR4193" roadName="PRR" roadNumber="4193" type="FM" length="40" color="Red" weight="2" weightTons="40" locationId="8" secLocationId="8s2" moves="0" date="" selected="false" load="E" />
    <car id="PRR4414" roadName="PRR" roadNumber="4414" type="P70" length="40" color="Red" weight="2" weightTons="40" locationId="10" secLocationId="10s9" moves="0" date="" selected="false" load="E" />
    <car id="PRR4472" roadName="PRR" roadNumber="4472" type="TM" length="40" color="Red" weight="2" weightTons="40" locationId="7" secLocationId="7s2" moves="0" date="" selected="false" load="E" />
    <car id="PRR4478" roadName="PRR" roadNumber="4478" type="GB" length="40" color="Red" weight="2" weightTons="40" locationId="11" secLocationId="11s4" moves="0" date="" selected="false" load="E" />
    <car id="PRR4752" roadName="PRR" roadNumber="4752" type="XM" length="40" color="Red" weight="2" weightTons="40" locationId="11" secLocationId="11s4" moves="0" date="" selected="false" load="E" />
    <car id="PRR4766" roadName="PRR" roadNumber="4766" type="XM" length="40" color="Red" weight="2" weightTons="40" locationId="11" secLocationId="11s2" moves="0" date="" selected="false" load="E" />
    <car id="PRR4843" roadName="PRR" roadNumber="4843" type="XX" length="40" color="Red" weight="2" weightTons="40" locationId="2" secLocationId="2s6" moves="0" date="" selected="false" load="express" />
    <car id="PRR4961" roadName="PRR" roadNumber="4961" type="FM" length="40" color="Red" weight="2" weightTons="40" locationId="11" secLocationId="11s1" moves="0" date="" selected="false" load="E" />
    <car id="PRR4973" roadName="PRR" roadNumber="4973" type="P70" length="40" color="Red" weight="2" weightTons="40" locationId="8" secLocationId="8s3" moves="0" date="" selected="false" load="E" />
    <car id="PRR5021" roadName="PRR" roadNumber="5021" type="P70" length="40" color="Red" weight="2" weightTons="40" locationId="8" secLocationId="8s3" moves="0" date="" selected="false" load="E" />
    <car id="PRR5042" roadName="PRR" roadNumber="5042" type="XM" length="40" color="Red" weight="2" weightTons="40" locationId="9" secLocationId="9s2" moves="0" date="" selected="false" load="E" />
    <car id="PRR506" roadName="PRR" roadNumber="506" type="NE" length="40" color="Red" weight="2" weightTons="36" locationId="12" secLocationId="12s3" moves="0" date="" selected="false" caboose="true" load="E" />
    <car id="PRR5189" roadName="PRR" roadNumber="5189" type="XX" length="40" color="Red" weight="2" weightTons="40" locationId="2" secLocationId="2s6" moves="0" date="" selected="false" load="express" />
    <car id="PRR5250" roadName="PRR" roadNumber="5250" type="XM" length="40" color="Red" weight="2" weightTons="40" locationId="11" secLocationId="11s3" moves="0" date="" selected="false" load="E" />
    <car id="PRR5281" roadName="PRR" roadNumber="5281" type="B60" length="40" color="Red" weight="2" weightTons="36" locationId="9" secLocationId="9s4" moves="0" date="" selected="false" passenger="true" load="E" />
    <car id="PRR5369" roadName="PRR" roadNumber="5369" type="MA" length="40" color="Red" weight="2" weightTons="36" locationId="2" secLocationId="2s6" moves="0" date="" selected="false" passenger="true" load="mail" />
    <car id="PRR540" roadName="PRR" roadNumber="540" type="NE" length="40" color="Red" weight="2" weightTons="36" locationId="9" secLocationId="9s2" moves="0" date="" selected="false" caboose="true" load="E" />
    <car id="PRR5426" roadName="PRR" roadNumber="5426" type="B60" length="40" color="Red" weight="2" weightTons="36" locationId="8" secLocationId="8s3" moves="0" date="" selected="false" passenger="true" load="E" />
    <car id="PRR5466" roadName="PRR" roadNumber="5466" type="P54" length="40" color="Red" weight="2" weightTons="40" locationId="10" secLocationId="10s9" moves="0" date="" selected="false" load="E" />
    <car id="PRR5836" roadName="PRR" roadNumber="5836" type="XX" length="40" color="Red" weight="2" weightTons="40" locationId="9" secLocationId="9s4" moves="0" date="" selected="false" load="E" />
    <car id="PRR5992" roadName="PRR" roadNumber="5992" type="GB" length="40" color="Red" weight="2" weightTons="40" locationId="11" secLocationId="11s2" moves="0" date="" selected="false" load="E" />
    <car id="PRR6115" roadName="PRR" roadNumber="6115" type="HK" length="40" color="Red" weight="2" weightTons="40" locationId="11" secLocationId="11s3" moves="0" date="" selected="false" load="E" />
    <car id="PRR6262" roadName="PRR" roadNumber="6262" type="GB" length="40" color="Red" weight="2" weightTons="40" locationId="11" secLocationId="11s3" moves="0" date="" selected="false" load="E" />
    <car id="PRR6279" roadName="PRR" roadNumber="6279" type="P70" length="40" color="Red" weight="2" weightTons="40" locationId="8" secLocationId="8s3" moves="0" date="" selected="false" load="E" />
    <car id="PRR6418" roadName="PRR" roadNumber="6418" type="MA" length="40" color="Red" weight="2" weightTons="36" locationId="9" secLocationId="9s4" moves="0" date="" selected="false" passenger="true" load="E" />
    <car id="PRR6446" roadName="PRR" roadNumber="6446" type="HK" length="40" color="Red" weight="2" weightTons="40" locationId="4" secLocationId="4s1" moves="0" date="" selected="false" load="E" />
    <car id="PRR6485" roadName="PRR" roadNumber="6485" type="CA" length="40" color="Red" weight="2" weightTons="36" locationId="2" secLocationId="2s8" moves="0" date="" selected="false" passenger="true" load="E" />
    <car id="PRR6558" roadName="PRR" roadNumber="6558" type="XM" length="40" color="Red" weight="2" weightTons="40" locationId="9" secLocationId="9s2" moves="0" date="" selected="false" load="E" />
    <car id="PRR6854" roadName="PRR" roadNumber="6854" type="B60" length="40" color="Red" weight="2" weightTons="36" locationId="2" secLocationId="2s7" moves="0" date="" selected="false" passenger="true" load="E" />
    <car id="PRR689" roadName="PRR" roadNumber="689" type="NM" length="40" color="Red" weight="2" weightTons="36" locationId="6" secLocationId="6s5" moves="0" date="" selected="false" caboose="true" load="E" />
    <car id="PRR6929" roadName="PRR" roadNumber="6929" type="XX" length="40" color="Red" weight="2" weightTons="40" locationId="3" secLocationId="3s3" moves="0" date="" selected="false" load="E" />
    <car id="PRR6999" roadName="PRR" roadNumber="6999" type="FM" length="40" color="Red" weight="2" weightTons="40" locationId="2" secLocationId="2s5" moves="0" date="" selected="false" load="Empty" />
    <car id="PRR7049" roadName="PRR" roadNumber="7049" type="XM" length="40" color="Red" weight="2" weightTons="40" locationId="8" secLocationId="8s2" moves="0" date="" selected="false" load="E" />
    <car id="PRR7291" roadName="PRR" roadNumber="7291" type="XM" length="40" color="Red" weight="2" weightTons="40" locationId="11" secLocationId="11s4" moves="0" date="" selected="false" load="E" />
    <car id="PRR7303" roadName="PRR" roadNumber="7303" type="Pk" length="40" color="Red" weight="2" weightTons="40" locationId="10" secLocationId="10s9" moves="0" date="" selected="false" load="E" />
    <car id="PRR7333" roadName="PRR" roadNumber="7333" type="GB" length="40" color="Red" weight="2" weightTons="40" locationId="11" secLocationId="11s3" moves="0" date="" selected="false" load="E" />
    <car id="PRR7387" roadName="PRR" roadNumber="7387" type="P70" length="40" color="Red" weight="2" weightTons="40" locationId="8" secLocationId="8s3" moves="0" date="" selected="false" load="E" />
    <car id="PRR7396" roadName="PRR" roadNumber="7396" type="HK" length="40" color="Red" weight="2" weightTons="40" locationId="8" secLocationId="8s2" moves="0" date="" selected="false" load="E" />
    <car id="PRR7481" roadName="PRR" roadNumber="7481" type="HK" length="40" color="Red" weight="2" weightTons="40" locationId="8" secLocationId="8s2" moves="0" date="" selected="false" load="E" />
    <car id="PRR7482" roadName="PRR" roadNumber="7482" type="TM" length="40" color="Red" weight="2" weightTons="40" locationId="11" secLocationId="11s4" moves="0" date="" selected="false" load="E" />
    <car id="PRR7541" roadName="PRR" roadNumber="7541" type="GB" length="40" color="Red" weight="2" weightTons="40" locationId="11" secLocationId="11s2" moves="0" date="" selected="false" load="E" />
    <car id="PRR7808" roadName="PRR" roadNumber="7808" type="XX" length="40" color="Red" weight="2" weightTons="40" locationId="4" secLocationId="4s1" moves="0" date="" selected="false" load="E" />
    <car id="PRR7863" roadName="PRR" roadNumber="7863" type="B60" length="40" color="Red" weight="2" weightTons="36" locationId="8" secLocationId="8s3" moves="0" date="" selected="false" passenger="true" load="E" />
    <car id="PRR7874" roadName="PRR" roadNumber="7874" type="Bd" length="40" color="Red" weight="2" weightTons="36" locationId="9" secLocationId="9s4" moves="0" date="" selected="false" passenger="true" load="E" />
    <car id="PRR7954" roadName="PRR" roadNumber="7954" type="XM" length="40" color="Red" weight="2" weightTons="40" locationId="9" secLocationId="9s2" moves="0" date="" selected="false" load="E" />
    <car id="PRR8020" roadName="PRR" roadNumber="8020" type="B60" length="40" color="Red" weight="2" weightTons="36" locationId="2" secLocationId="2s6" moves="0" date="" selected="false" passenger="true" load="express" />
    <car id="PRR8057" roadName="PRR" roadNumber="8057" type="B60" length="40" color="Red" weight="2" weightTons="36" locationId="2" secLocationId="2s6" moves="0" date="" selected="false" passenger="true" load="express" />
    <car id="PRR8102" roadName="PRR" roadNumber="8102" type="B60" length="40" color="Red" weight="2" weightTons="36" locationId="2" secLocationId="2s6" moves="0" date="" selected="false" passenger="true" load="express" />
    <car id="PRR8322" roadName="PRR" roadNumber="8322" type="XM" length="40" color="Red" weight="2" weightTons="40" locationId="5" secLocationId="5s2" moves="0" date="" selected="false" load="goods" />
    <car id="PRR8587" roadName="PRR" roadNumber="8587" type="PS" length="40" color="Red" weight="2" weightTons="36" locationId="2" secLocationId="2s7" moves="0" date="" selected="false" passenger="true" load="E" />
    <car id="PRR8639" roadName="PRR" roadNumber="8639" type="XM" length="40" color="Red" weight="2" weightTons="40" locationId="9" secLocationId="9s2" moves="0" date="" selected="false" load="E" />
    <car id="PRR8836" roadName="PRR" roadNumber="8836" type="GB" length="40" color="Red" weight="2" weightTons="40" locationId="8" secLocationId="8s2" moves="0" date="" selected="false" load="E" />
    <car id="PRR8860" roadName="PRR" roadNumber="8860" type="HK" length="40" color="Red" weight="2" weightTons="40" locationId="3" secLocationId="3s1" moves="0" date="" selected="false" load="Empty" />
    <car id="PRR8869" roadName="PRR" roadNumber="8869" type="P70" length="40" color="Red" weight="2" weightTons="40" locationId="10" secLocationId="10s9" moves="0" date="" selected="false" load="E" />
    <car id="PRR8919" roadName="PRR" roadNumber="8919" type="MA" length="40" color="Red" weight="2" weightTons="36" locationId="9" secLocationId="9s4" moves="0" date="" selected="false" passenger="true" load="E" />
    <car id="PRR9167" roadName="PRR" roadNumber="9167" type="XM" length="40" color="Red" weight="2" weightTons="40" locationId="9" secLocationId="9s2" moves="0" date="" selected="false" load="E" />
    <car id="PRR9505" roadName="PRR" roadNumber="9505" type="P70" length="40" color="Red" weight="2" weightTons="40" locationId="10" secLocationId="10s9" moves="0" date="" selected="false" load="E" />
    <car id="PRR9542" roadName="PRR" roadNumber="9542" type="XX" length="40" color="Red" weight="2" weightTons="40" locationId="8" secLocationId="8s3" moves="0" date="" selected="false" load="E" />
    <car id="PRR9880" roadName="PRR" roadNumber="9880" type="XM" length="40" color="Red" weight="2" weightTons="40" locationId="11" secLocationId="11s2" moves="0" date="" selected="false" load="E" />
    <car id="PRRMoW496" roadName="PRRMoW" roadNumber="496" type="MWK" length="40" color="Red" weight="2" weightTons="40" locationId="6" secLocationId="6s5" moves="0" date="" selected="false" load="E" />
    <car id="SP2604" roadName="SP" roadNumber="2604" type="XM" length="40" color="Red" weight="2" weightTons="40" locationId="9" secLocationId="9s2" moves="0" date="" selected="false" load="E" />
    <car id="SP2996" roadName="SP" roadNumber="2996" type="GB" length="40" color="Red" weight="2" weightTons="40" locationId="2" secLocationId="2s4" moves="0" date="" selected="false" load="Empty" />
    <car id="SP7403" roadName="SP" roadNumber="7403" type="GB" length="40" color="Red" weight="2" weightTons="40" locationId="2" secLocationId="2s5" moves="0" date="" selected="false" load="Empty" />
    <car id="TCX0510" roadName="TCX" roadNumber="0510" type="TM" length="40" color="Red" weight="2" weightTons="40" locationId="11" secLocationId="11s3" moves="0" date="" selected="false" load="E" />
    <car id="TCX1116" roadName="TCX" roadNumber="1116" type="TM" length="40" color="Red" weight="2" weightTons="40" locationId="11" secLocationId="11s4" moves="0" date="" selected="false" load="E" />
    <car id="TCX2539" roadName="TCX" roadNumber="2539" type="TM" length="40" color="Red" weight="2" weightTons="40" locationId="9" secLocationId="9s2" moves="0" date="" selected="false" load="E" />
    <car id="TCX2717" roadName="TCX" roadNumber="2717" type="TM" length="40" color="Red" weight="2" weightTons="40" locationId="8" secLocationId="8s2" moves="0" date="" selected="false" load="E" />
    <car id="TCX2904" roadName="TCX" roadNumber="2904" type="TM" length="40" color="Red" weight="2" weightTons="40" locationId="11" secLocationId="11s4" moves="0" date="" selected="false" load="E" />
    <car id="TCX5207" roadName="TCX" roadNumber="5207" type="TM" length="40" color="Red" weight="2" weightTons="40" locationId="7" secLocationId="7s2" moves="0" date="" selected="false" load="E" />
    <car id="TCX5324" roadName="TCX" roadNumber="5324" type="TM" length="40" color="Red" weight="2" weightTons="40" locationId="8" secLocationId="8s2" moves="0" date="" selected="false" load="E" />
    <car id="TCX7210" roadName="TCX" roadNumber="7210" type="TM" length="40" color="Red" weight="2" weightTons="40" locationId="11" secLocationId="11s2" moves="0" date="" selected="false" load="E" />
    <car id="TELX0113" roadName="TELX" roadNumber="0113" type="TM" length="40" color="Red" weight="2" weightTons="40" locationId="7" secLocationId="7s2" moves="0" date="" selected="false" load="E" />
    <car id="TELX2341" roadName="TELX" roadNumber="2341" type="TM" length="40" color="Red" weight="2" weightTons="40" locationId="8" secLocationId="8s2" moves="0" date="" selected="false" load="E" />
    <car id="TELX4330" roadName="TELX" roadNumber="4330" type="TM" length="40" color="Red" weight="2" weightTons="40" locationId="11" secLocationId="11s4" moves="0" date="" selected="false" load="E" />
    <car id="TELX8228" roadName="TELX" roadNumber="8228" type="TM" length="40" color="Red" weight="2" weightTons="40" locationId="11" secLocationId="11s4" moves="0" date="" selected="false" load="E" />
    <car id="TELX8870" roadName="TELX" roadNumber="8870" type="TM" length="40" color="Red" weight="2" weightTons="40" locationId="7" secLocationId="7s2" moves="0" date="" selected="false" load="E" />
    <car id="UTLX1758" roadName="UTLX" roadNumber="1758" type="TM" length="40" color="Red" weight="2" weightTons="40" locationId="11" secLocationId="11s3" moves="0" date="" selected="false" load="E" />
    <car id="UTLX4974" roadName="UTLX" roadNumber="4974" type="TM" length="40" color="Red" weight="2" weightTons="40" locationId="8" secLocationId="8s2" moves="0" date="" selected="false" load="E" />
    <car id="UTLX7588" roadName="UTLX" roadNumber="7588" type="TM" length="40" color="Red" weight="2" weightTons="40" locationId="8" secLocationId="8s2" moves="0" date="" selected="false" load="E" />
    <car id="UTLX7837" roadName="UTLX" roadNumber="7837" type="TM" length="40" color="Red" weight="2" weightTons="40" locationId="11" secLocationId="11s4" moves="0" date="" selected="false" load="E" />
    <car id="UTLX9520" roadName="UTLX" roadNumber="9520" type="TM" length="40" color="Red" weight="2" weightTons="40" locationId="9" secLocationId="9s2" moves="0" date="" selected="false" load="E" />
    <car id="UTLX9649" roadName="UTLX" roadNumber="9649" type="TM" length="40" color="Red" weight="2" weightTons="40" locationId="5" secLocationId="5s7" moves="0" date="" selected="false" load="Empty" />
    <car id="WCC1472" roadName="WCC" roadNumber="1472" type="HK" length="40" color="Red" weight="2" weightTons="40" locationId="8" secLocationId="8s2" moves="0" date="" selected="false" load="E" />
    <car id="WCC7193" roadName="WCC" roadNumber="7193" type="HK" length="40" color="Red" weight="2" weightTons="40" locationId="9" secLocationId="9s2" moves="0" date="" selected="false" load="E" />
    <car id="WJ&amp;S2288" roadName="WJ&amp;S" roadNumber="2288" type="XM" length="40" color="Red" weight="2" weightTons="40" locationId="9" secLocationId="9s2" moves="0" date="" selected="false" load="E" />
    <car id="WJ&amp;S2774" roadName="WJ&amp;S" roadNumber="2774" type="XM" length="40" color="Red" weight="2" weightTons="40" locationId="5" secLocationId="5s5" moves="0" date="" selected="false" load="goods" />
    <car id="WJ&amp;S3080" roadName="WJ&amp;S" roadNumber="3080" type="XM" length="40" color="Red" weight="2" weightTons="40" locationId="11" secLocationId="11s5" moves="0" date="" selected="false" load="E" />
    <car id="WJ&amp;S3268" roadName="WJ&amp;S" roadNumber="3268" type="XM" length="40" color="Red" weight="2" weightTons="40" locationId="11" secLocationId="11s3" moves="0" date="" selected="false" load="E" />
    <car id="WJ&amp;S3512" roadName="WJ&amp;S" roadNumber="3512" type="GB" length="40" color="Red" weight="2" weightTons="40" locationId="11" secLocationId="11s1" moves="0" date="" selected="false" load="E" />
    <car id="WJ&amp;S3565" roadName="WJ&amp;S" roadNumber="3565" type="XM" length="40" color="Red" weight="2" weightTons="40" locationId="7" secLocationId="7s2" moves="0" date="" selected="false" load="E" />
    <car id="WJ&amp;S4217" roadName="WJ&amp;S" roadNumber="4217" type="GB" length="40" color="Red" weight="2" weightTons="40" locationId="8" secLocationId="8s2" moves="0" date="" selected="false" load="E" />
    <car id="WJ&amp;S4790" roadName="WJ&amp;S" roadNumber="4790" type="FM" length="40" color="Red" weight="2" weightTons="40" locationId="8" secLocationId="8s2" moves="0" date="" selected="false" load="E" />
    <car id="WJ&amp;S5624" roadName="WJ&amp;S" roadNumber="5624" type="XM" length="40" color="Red" weight="2" weightTons="40" locationId="9" secLocationId="9s2" moves="0" date="" selected="false" load="E" />
    <car id="WJ&amp;S5720" roadName="WJ&amp;S" roadNumber="5720" type="XM" length="40" color="Red" weight="2" weightTons="40" locationId="11" secLocationId="11s2" moves="0" date="" selected="false" load="E" />
    <car id="WJ&amp;S6658" roadName="WJ&amp;S" roadNumber="6658" type="XM" length="40" color="Red" weight="2" weightTons="40" locationId="9" secLocationId="9s2" moves="0" date="" selected="false" load="E" />
    <car id="WJ&amp;S6707" roadName="WJ&amp;S" roadNumber="6707" type="XM" length="40" color="Red" weight="2" weightTons="40" locationId="11" secLocationId="11s2" moves="0" date="" selected="false" load="E" />
    <car id="WJ&amp;S7368" roadName="WJ&amp;S" roadNumber="7368" type="GB" length="40" color="Red" weight="2" weightTons="40" locationId="9" secLocationId="9s2" moves="0" date="" selected="false" load="E" />
    <car id="WJ&amp;S8346" roadName="WJ&amp;S" roadNumber="8346" type="XM" length="40" color="Red" weight="2" weightTons="40" locationId="8" secLocationId="8s2" moves="0" date="" selected="false" load="E" />
    <car id="WJ&amp;S8765" roadName="WJ&amp;S" roadNumber="8765" type="XM" length="40" color="Red" weight="2" weightTons="40" locationId="5" secLocationId="5s2" moves="0" date="" selected="false" load="goods" />
    <car id="WJ&amp;S9592" roadName="WJ&amp;S" roadNumber="9592" type="GB" length="40" color="Red" weight="2" weightTons="40" locationId="11" secLocationId="11s1" moves="0" date="" selected="false" load="E" />
  </cars>
</operations-config>
